Metadata-Version: 2.1
Name: AuthCore
Version: 0.1.0
Summary: AuthCore
Home-page: UNKNOWN
Author: Theta
License: UNKNOWN
Platform: UNKNOWN
